{
  "headers": {
    "content-length": "259",
    "date": "Sun, 30 Jan 2022 17:20:30 GMT",
    "last-modified": "Fri, 29 Jan 2021 14:54:17 GMT",
    "cache-control": "public, max-age=31536000, immutable",
    "content-type": "application/typescript; charset=utf-8",
    "x-amz-request-id": "V2T7HBNB1AFMK2DY",
    "access-control-allow-origin": "*",
    "x-amz-id-2": "tVLqYZHA7kv4ajn24j2VkhoExfsvXfjianwxDWdCmfqw4h2P7hYWyO7eyNQfMF0/Im8kOzeh1B4=",
    "server": "deploy/us-central1-b",
    "etag": "\"49cabf94e5bf1cea284f1df0cb1380aa\"",
    "x-amz-version-id": "kx3AYdSMBVgZmeO3x45ic6oyQMjNAxQs"
  },
  "url": "https://deno.land/std@0.85.0/path/separator.ts",
  "now": {
    "secs_since_epoch": 1643563230,
    "nanos_since_epoch": 4581330
  }
}