{
  "headers": {
    "access-control-allow-origin": "*",
    "x-amz-request-id": "E0PE6PPR0165Q3FS",
    "date": "Sun, 30 Jan 2022 17:20:31 GMT",
    "server": "deploy/us-central1-b",
    "content-type": "application/javascript",
    "x-amz-id-2": "sz7cuIUe2ghYdG2M2osxfLdAtP+Ovzcv/UTFeSOOpbfH/g3vezWIMDNztl3i4VpjE8XiKzzlX70=",
    "x-amz-version-id": "null",
    "etag": "\"16bf6847de4a200aafd72ec8e81b4c56\"",
    "last-modified": "Sat, 29 Aug 2020 19:56:47 GMT",
    "content-length": "562",
    "cache-control": "public, max-age=31536000, immutable"
  },
  "url": "https://deno.land/x/lodash@4.17.15-es/_isMasked.js",
  "now": {
    "secs_since_epoch": 1643563230,
    "nanos_since_epoch": 173473470
  }
}