{
  "headers": {
    "etag": "\"6f03250e6887dabb4fcf8216ae90d356\"",
    "access-control-allow-origin": "*",
    "x-amz-version-id": "PJfnKzEojm4z4aoKNtAU_iVxjf6CkSuc",
    "server": "deploy/asia-northeast2-c",
    "last-modified": "Fri, 25 Sep 2020 14:55:01 GMT",
    "x-amz-request-id": "RWAZVHTM6YY1W0GV",
    "content-type": "application/typescript; charset=utf-8",
    "content-length": "8319",
    "date": "Fri, 04 Feb 2022 18:11:02 GMT",
    "x-amz-id-2": "AxLJ2WFv7uyV/MIhWtJAjcLww1ZLwHnT73qDX2Nv+r+Uwzn/YCm/jp+2G5zBqYYD3J0cS/zjTlw=",
    "cache-control": "public, max-age=31536000, immutable"
  },
  "url": "https://deno.land/std@0.71.0/path/glob.ts",
  "now": {
    "secs_since_epoch": 1643998261,
    "nanos_since_epoch": 478270000
  }
}